katcp_codec-0.2.0.dist-info/RECORD
katcp_codec-0.2.0.dist-info/WHEEL
katcp_codec-0.2.0.dist-info/top_level.txt
katcp_codec-0.2.0.dist-info/METADATA
katcp_codec/_lib.cpython-39-darwin.so
katcp_codec/__init__.py
katcp_codec/py.typed
katcp_codec/_lib.pyi
