Metadata-Version: 2.4
Name: katcp-codec
Version: 0.2.0
Summary: Fast encoding and decoding of katcp messages
Author-email: Bruce Merry <bmerry@sarao.ac.za>
Project-URL: Homepage, https://github.com/ska-sa/katcp-codec
Keywords: katcp
Classifier: Development Status :: 3 - Alpha
Classifier: License :: OSI Approved :: BSD License
Requires-Python: >=3.8
Requires-Dist: typing-extensions
Provides-Extra: dev
Requires-Dist: pre-commit; extra == "dev"
Requires-Dist: pytest; extra == "dev"
Requires-Dist: build; extra == "dev"
Provides-Extra: doc
Requires-Dist: sphinx; extra == "doc"
Requires-Dist: sphinxcontrib-tikz; extra == "doc"
Requires-Dist: sphinx-rtd-theme; extra == "doc"
